llmrelic/__init__.py
llmrelic/capabilities.py
llmrelic/finder.py
llmrelic/metadata.py
llmrelic/models.py
llmrelic/registry.py
llmrelic-0.2.3.dist-info/METADATA
llmrelic-0.2.3.dist-info/WHEEL
llmrelic-0.2.3.dist-info/top_level.txt
llmrelic-0.2.3.dist-info/RECORD
