Metadata-Version: 2.4
Name: llmrelic
Version: 0.2.3
Summary: A lightweight Python library providing easy access to popular LLM model names, metadata (context windows, capabilities, pricing tiers), and support definitions. Born from a failed experiment on context data compression for LLMs with finite context windows, this library helps developers manage model names, validate support, search by capabilities, and find models by requirements without hardcoding strings or maintaining spreadsheets.
Author-email: OVECJOE <vohachor@gmail.com>
License: MIT
Project-URL: Bug Reports, https://github.com/OVECJOE/llmrelic/issues
Project-URL: Source, https://github.com/OVECJOE/llmrelic
Keywords: llm,ai,models,registry,openai,anthropic,google,cohere,mistral,meta,huggingface
Classifier: Development Status :: 3 - Alpha
Classifier: Intended Audience :: Developers
Classifier: Operating System :: OS Independent
Classifier: Programming Language :: Python :: 3
Classifier: Programming Language :: Python :: 3.8
Classifier: Programming Language :: Python :: 3.9
Classifier: Programming Language :: Python :: 3.10
Classifier: Programming Language :: Python :: 3.11
Classifier: Topic :: Software Development :: Libraries :: Python Modules
Classifier: Topic :: Scientific/Engineering :: Artificial Intelligence
Requires-Python: >=3.8
Requires-Dist: pytest>=8.3.5
Provides-Extra: dev
Requires-Dist: pytest; extra == "dev"
Requires-Dist: black; extra == "dev"
Requires-Dist: flake8; extra == "dev"
Requires-Dist: mypy; extra == "dev"
Requires-Dist: twine; extra == "dev"
